bluesheep
