Metadata-Version: 2.1
Name: bluesheep
Version: 0.0.3
Summary: HTTP Server/Client microframework for Python asyncio
Home-page: https://github.com/RobertoPrevato/BlueSheep
Author: Roberto Prevato
Author-email: roberto.prevato@gmail.com
License: MIT
Keywords: BlueSheep web framework
Platform: *nix
Classifier: Development Status :: 3 - Alpha
Classifier: License :: OSI Approved :: MIT License
Classifier: Programming Language :: Python :: 3.7
Classifier: Operating System :: OS Independent
Classifier: Framework :: AsyncIO
